srvres/__init__.py
srvres/resolver.py
srvres/service_ports.py
srvres/utils.py
srvres-1.0.0.dist-info/LICENSE
srvres-1.0.0.dist-info/WHEEL
srvres-1.0.0.dist-info/METADATA
srvres-1.0.0.dist-info/RECORD
