Metadata-Version: 2.1
Name: srvres
Version: 1.0.0
Summary: A somewhat simple-- yet useful-- SRV resolver in around 100 lines of Python code.
Home-page: https://github.com/MineRobber9000/srvres
License: MIT
Author: Robert "khuxkm" Miles
Author-email: khuxkm+srvres@tilde.team
Classifier: Development Status :: 5 - Production/Stable
Classifier: License :: OSI Approved :: MIT License
Classifier: Programming Language :: Python :: 2
Classifier: Programming Language :: Python :: 2.7
Classifier: Programming Language :: Python :: 3
Classifier: Programming Language :: Python :: 3.4
Classifier: Programming Language :: Python :: 3.5
Classifier: Programming Language :: Python :: 3.6
Classifier: Programming Language :: Python :: 3.7
Classifier: Programming Language :: Python :: 3.8
Classifier: Programming Language :: Python :: 3.9
Requires-Dist: dnspython
Project-URL: Repository, https://github.com/MineRobber9000/srvres
